constantly/__init__.py
constantly/_constants.py
constantly/_version.py
constantly/constants.py
constantly-15.0.0.dist-info/DESCRIPTION.rst
constantly-15.0.0.dist-info/METADATA
constantly-15.0.0.dist-info/metadata.json
constantly-15.0.0.dist-info/pbr.json
constantly-15.0.0.dist-info/RECORD
constantly-15.0.0.dist-info/top_level.txt
constantly-15.0.0.dist-info/WHEEL
