Metadata-Version: 2.0
Name: constantly
Version: 15.0.0
Summary: Symbolic constants in Python
Home-page: https://github.com/twisted/constantly
Author: Twisted Matrix Labs Developers
Author-email: UNKNOWN
License: MIT
Keywords: constants,enum,twisted
Platform: UNKNOWN
Classifier: Intended Audience :: Developers
Classifier: License :: OSI Approved :: MIT License
Classifier: Operating System :: OS Independent
Classifier: Programming Language :: Python
Classifier: Programming Language :: Python :: 2.6
Classifier: Programming Language :: Python :: 2.7
Classifier: Programming Language :: Python :: Implementation :: CPython
Classifier: Programming Language :: Python :: Implementation :: PyPy
Classifier: Topic :: Software Development :: Libraries :: Python Modules
